db_queryset_tools_pkg/__init__.py
db_queryset_tools_pkg/db_queryset_tools.py
db_queryset_tools_pkg-1.0.0.dist-info/LICENSE
db_queryset_tools_pkg-1.0.0.dist-info/METADATA
db_queryset_tools_pkg-1.0.0.dist-info/WHEEL
db_queryset_tools_pkg-1.0.0.dist-info/top_level.txt
db_queryset_tools_pkg-1.0.0.dist-info/RECORD
