Metadata-Version: 2.1
Name: db_queryset_tools_pkg
Version: 1.0.0
Summary: A package to convert Django Queryset to list, dictionary, json and dataset for charts
Home-page: https://github.com/Hariharan-Sathiyamoorthy/db_queryset_tools
Author: Hariharan Sathiyamoorthy
Author-email: hari.rn03@gmail.com
Classifier: Programming Language :: Python :: 3
Classifier: License :: OSI Approved :: MIT License
Classifier: Operating System :: OS Independent
Requires-Python: >=3.6
License-File: LICENSE
Requires-Dist: Django
